turandot/__init__.py
turandot/__main__.py
turandot/exceptions.py
turandot/meta.py
turandot/sysinfo.py
turandot/assets/__init__.py
turandot/assets/about.txt
turandot/assets/default.yaml
turandot/assets/gtk4.css
turandot/assets/turandot.desktop
turandot/assets/turandot.png
turandot/assets/turandot.sh
turandot/assets/turandot.svg
turandot/assets/uninstall.sh
turandot/assets/update.sh
turandot/assets/windows_fonts.conf
turandot/assets/extract/__init__.py
turandot/assets/extract/__main__.py
turandot/gtk4/__init__.py
turandot/gtk4/__main__.py
turandot/gtk4/catcher.py
turandot/gtk4/enumlocalization.py
turandot/gtk4/filefilters.py
turandot/gtk4/guithread.py
turandot/gtk4/mainwindow.py
turandot/gtk4/controllers/__init__.py
turandot/gtk4/controllers/basecontroller.py
turandot/gtk4/controllers/conversionupdater.py
turandot/gtk4/controllers/convertercontroller.py
turandot/gtk4/controllers/cslcontroller.py
turandot/gtk4/controllers/headerbarcontroller.py
turandot/gtk4/controllers/templatecontroller.py
turandot/gtk4/dialogs/__init__.py
turandot/gtk4/dialogs/aboutdialog.py
turandot/gtk4/dialogs/confirmationdialog.py
turandot/gtk4/dialogs/errordialog.py
turandot/gtk4/dialogs/filechooser.py
turandot/gtk4/dialogs/settingsdialog.py
turandot/gtk4/dialogs/templateeditor.py
turandot/gtk4/presentations/__init__.py
turandot/gtk4/presentations/enumdropdown.py
turandot/gtk4/presentations/observerdropdown.py
turandot/gtk4/presentations/observerlistviews.py
turandot/gtk4/presentations/settingspresentation.py
turandot/gtk4/representations/__init__.py
turandot/gtk4/representations/dbobservables.py
turandot/gtk4/representations/observerbase.py
turandot/gtk4/views/__init__.py
turandot/gtk4/views/convertertab.py
turandot/gtk4/views/csltab.py
turandot/gtk4/views/headerbarview.py
turandot/gtk4/views/templatetab.py
turandot/gtk4/views/viewcomponent.py
turandot/model/__init__.py
turandot/model/util.py
turandot/model/zoteroconnector.py
turandot/model/config/__init__.py
turandot/model/config/config.py
turandot-3.1.5.dist-info/LICENSE.txt
turandot-3.1.5.dist-info/METADATA
turandot-3.1.5.dist-info/WHEEL
turandot-3.1.5.dist-info/top_level.txt
turandot-3.1.5.dist-info/RECORD
