Metadata-Version: 2.1
Name: turandot
Version: 3.1.5
Summary: Turandot Markdown Converter
Home-page: https://turandot.readthedocs.io
Author: Martin Obrist
Author-email: dev@obrist.email
License: GPLv3
Project-URL: Documentation, https://turandot.readthedocs.io
Project-URL: Source Code, https://gitlab.com/dinuthehuman/turandot
Project-URL: Issue Tracker, https://gitlab.com/dinuthehuman/turandot/-/issues
Keywords: markdown,citeproc
Classifier: Development Status :: 5 - Production/Stable
Classifier: Topic :: Text Processing :: Markup :: Markdown
Classifier: License :: OSI Approved :: GNU General Public License v3 (GPLv3)
Classifier: Operating System :: OS Independent
Classifier: Programming Language :: Python :: 3
Classifier: Programming Language :: Python :: 3 :: Only
Requires-Python: >=3.10, <4
License-File: LICENSE.txt
Requires-Dist: beautifulsoup4 (==4.11.2)
Requires-Dist: colour (==0.1.5)
Requires-Dist: jinja2 (==3.1.3)
Requires-Dist: lxml (==5.1.0)
Requires-Dist: Mako (==1.2.4)
Requires-Dist: markdown (==3.5.2)
Requires-Dist: markdown-captions (==2.1.2)
Requires-Dist: markdown-katex (==202112.1034)
Requires-Dist: md-citeproc (==0.2.2)
Requires-Dist: Pygments (==2.17.2)
Requires-Dist: python-frontmatter (==1.0.0)
Requires-Dist: pyyaml (==6.0.1)
Requires-Dist: requests (==2.31.0)
Requires-Dist: ruamel.yaml (==0.18.6)
Requires-Dist: sqlalchemy (==2.0.27)
Requires-Dist: urllib3 (==2.2.1)
Requires-Dist: weasyprint (==56.0)
Provides-Extra: dev
Requires-Dist: gitpython (==3.1.42) ; extra == 'dev'
Requires-Dist: mkdocs (==1.5.3) ; extra == 'dev'
Requires-Dist: mkdocstrings (==0.24.1) ; extra == 'dev'
Requires-Dist: twine (==5.0.0) ; extra == 'dev'
Requires-Dist: pytest (==8.0.2) ; extra == 'dev'
Requires-Dist: nose (==1.3.7) ; extra == 'dev'
Requires-Dist: invoke (==2.2.0) ; extra == 'dev'
Provides-Extra: gtk
Requires-Dist: pygobject (==3.46.0) ; extra == 'gtk'
Provides-Extra: optional
Requires-Dist: gitpython (==3.1.42) ; extra == 'optional'
Requires-Dist: qrcode (==7.4.2) ; extra == 'optional'
Requires-Dist: swissqr (==0.2.0) ; extra == 'optional'
Provides-Extra: tk
Requires-Dist: tkhtmlview ; extra == 'tk'
Requires-Dist: bidict ; extra == 'tk'
